pasha_loh_2004/__init__.py
pasha_loh_2004-0.1.0.dist-info/METADATA
pasha_loh_2004-0.1.0.dist-info/WHEEL
pasha_loh_2004-0.1.0.dist-info/top_level.txt
pasha_loh_2004-0.1.0.dist-info/RECORD
