Metadata-Version: 2.4
Name: pasha-loh-2004
Version: 0.1.0
Summary: A hilarious Python lib by Pasha 😎
Author-email: Pasha <pasha@example.com>
License: MIT
Requires-Python: >=3.7
